pocketsearch/__init__.py
pocketsearch/tests.py
pocketsearch-0.41.0.dist-info/licenses/LICENSE
pocketsearch-0.41.0.dist-info/METADATA
pocketsearch-0.41.0.dist-info/WHEEL
pocketsearch-0.41.0.dist-info/top_level.txt
pocketsearch-0.41.0.dist-info/RECORD
