Metadata-Version: 2.4
Name: pocketsearch
Version: 0.41.0
Summary: A pure-Python full-text indexing search library based on SQLite and the FTS5 extension, supporting both on-disk and in-memory search indexes.
Home-page: https://github.com/kaykay-dv/pocketsearch/
Author: kaykay-dv
Author-email: kaykay2306@gmail.com
Project-URL: Bug Tracker, https://github.com/kaykay-dv/pocketsearch/issues
Project-URL: Change log, https://github.com/kaykay-dv/pocketsearch/blob/main/CHANGELOG.md
Project-URL: Documentation, https://pocketsearch.readthedocs.io/
Classifier: Development Status :: 5 - Production/Stable
Classifier: Natural Language :: English
Classifier: Programming Language :: Python :: 3.9
Classifier: Programming Language :: Python :: 3.10
Classifier: Programming Language :: Python :: 3.11
Classifier: Programming Language :: Python :: 3.12
Classifier: Programming Language :: Python :: 3.13
Classifier: Programming Language :: Python :: 3.14
Classifier: License :: OSI Approved :: MIT License
Classifier: Operating System :: OS Independent
Classifier: Intended Audience :: Developers
Classifier: Topic :: Software Development :: Libraries :: Python Modules
Classifier: Topic :: Text Processing :: Indexing
Requires-Python: >=3.8
License-File: LICENSE
Dynamic: author
Dynamic: author-email
Dynamic: classifier
Dynamic: description
Dynamic: description-content-type
Dynamic: home-page
Dynamic: license-file
Dynamic: project-url
Dynamic: requires-python
Dynamic: summary
